Metadata-Version: 2.1
Name: odoo12-addon-mail-improved-tracking-value
Version: 12.0.1.0.0.99.dev6
Summary: Improves tracking changed values for certain type of fields.Adds a user-friendly view to consult them.
Home-page: https://github.com/OCA/social
Author: Camptocamp, Odoo Community Association (OCA)
Author-email: support@odoo-community.org
License: AGPL-3
Platform: UNKNOWN
Classifier: Programming Language :: Python
Classifier: Framework :: Odoo
Classifier: Framework :: Odoo :: 12.0
Classifier: License :: OSI Approved :: GNU Affero General Public License v3
Requires-Python: >=3.5
Requires-Dist: odoo <12.1dev,>=12.0a
